eclipse_sumo-1.25.0.dist-info/licenses/AUTHORS
eclipse_sumo-1.25.0.dist-info/licenses/LICENSE
eclipse_sumo-1.25.0.dist-info/licenses/NOTICE.md
sumo/__init__.py
sumo/bin/activitygen
sumo/bin/dfrouter
sumo/bin/duarouter
sumo/bin/emissionsDrivingCycle
sumo/bin/emissionsMap
sumo/bin/jtrrouter
sumo/bin/marouter
sumo/bin/netconvert
sumo/bin/netedit
sumo/bin/netgenerate
sumo/bin/od2trips
sumo/bin/polyconvert
sumo/bin/sumo
sumo/bin/sumo-gui
sumo/cmake/SUMOConfig-release.cmake
sumo/cmake/SUMOConfig.cmake
sumo/data/3D/car-microcargo-citrus.mtl
sumo/data/3D/car-microcargo-citrus.obj
sumo/data/3D/car-minibus-citrus.mtl
sumo/data/3D/car-minibus-citrus.obj
sumo/data/3D/car-normal-citrus.mtl
sumo/data/3D/car-normal-citrus.obj
sumo/data/3D/humanResting.mtl
sumo/data/3D/humanResting.obj
sumo/data/3D/poleBase.obj
sumo/data/3D/tl.obj.mtl
sumo/data/3D/tlg.obj
sumo/data/3D/tlr.obj
sumo/data/3D/tlu.obj
sumo/data/3D/tly.obj
sumo/data/3D/tram.mtl
sumo/data/3D/tram.obj
sumo/data/emissions/MMPEVEM/BMW_i3.xml
sumo/data/emissions/MMPEVEM/Citroen_e-C4.rou.xml
sumo/data/emissions/MMPEVEM/Hyundai_Ioniq_5.rou.xml
sumo/data/emissions/MMPEVEM/Opel_Corsa_Electric.rou.xml
sumo/data/emissions/MMPEVEM/Opel_Mokka-e.rou.xml
sumo/data/emissions/MMPEVEM/Peugeot_e-2008.rou.xml
sumo/data/emissions/MMPEVEM/Peugeot_e-208.rou.xml
sumo/data/emissions/MMPEVEM/SUV.xml
sumo/data/emissions/MMPEVEM/VW_ID3.xml
sumo/data/emissions/MMPEVEM/VW_ID4.xml
sumo/data/emissions/MMPEVEM/VW_eUp.xml
sumo/data/emissions/PHEMlight/PC_D_EU4.PHEMLight.veh
sumo/data/emissions/PHEMlight/PC_D_EU4.csv
sumo/data/emissions/PHEMlight/PC_D_EU4_FC.csv
sumo/data/emissions/PHEMlight/PC_G_EU4.PHEMLight.veh
sumo/data/emissions/PHEMlight/PC_G_EU4.csv
sumo/data/emissions/PHEMlight/PC_G_EU4_FC.csv
sumo/data/emissions/PHEMlight5/Deterioration.det
sumo/data/emissions/PHEMlight5/Mileage.vma
sumo/data/emissions/PHEMlight5/NOxCor.tno
sumo/data/emissions/PHEMlight5/PC_EU4_D_MW.PHEMLight.veh
sumo/data/emissions/PHEMlight5/PC_EU4_D_MW.csv
sumo/data/emissions/PHEMlight5/PC_EU4_D_MW_FC.csv
sumo/data/emissions/PHEMlight5/PC_EU4_G.PHEMLight.veh
sumo/data/emissions/PHEMlight5/PC_EU4_G.csv
eclipse_sumo-1.25.0.dist-info/METADATA
eclipse_sumo-1.25.0.dist-info/WHEEL
eclipse_sumo-1.25.0.dist-info/entry_points.txt
eclipse_sumo-1.25.0.dist-info/top_level.txt
eclipse_sumo-1.25.0.dist-info/RECORD
