Metadata-Version: 2.4
Name: eclipse-sumo
Version: 1.25.0
Summary: A microscopic, multi-modal traffic simulation package
Home-page: https://sumo.dlr.de/
Download-URL: https://sumo.dlr.de/download
Author: DLR and contributors
Author-email: sumo@dlr.de
License: EPL-2.0
Keywords: traffic simulation traci sumo
Classifier: Development Status :: 5 - Production/Stable
Classifier: Intended Audience :: Developers
Classifier: Intended Audience :: Science/Research
Classifier: Programming Language :: C++
Classifier: Programming Language :: Python :: 2
Classifier: Programming Language :: Python :: 3
License-File: LICENSE
License-File: NOTICE.md
License-File: AUTHORS
Dynamic: author
Dynamic: author-email
Dynamic: classifier
Dynamic: description
Dynamic: description-content-type
Dynamic: download-url
Dynamic: home-page
Dynamic: keywords
Dynamic: license
Dynamic: license-file
Dynamic: summary
